{
  "name": "Maud Goodwin",
  "age": 39,
  "address": {
    "street": "Mocca Park",
    "city": "Fescugcim",
    "state": "NV",
    "zip": "01549"
  },
  "contact": {
    "phone": "(849) 878-6716",
    "servicePhone": "800472429"
  },
  "birthday": "1989-12-15T11:59:08.882Z",
  "ip": "23.15.6.252",
  "foo": "bar",
  "profile": {
    "about": "Zucoma si juwji oziem itgu kazcim nuvi vosoho nokel gapgode gu pubo bolespik mi. Natfoze waho vuz apuk wa cobi dacto soajievi ikunuusu uhlep abe darso he nemnac rikeloz hi efa. Ra afavikdo docomi hew jufeuci bapvin paz dov fi tu hiwhoz katrinew pofuwiz bipiw.",
    "bio": "Ka ukmoud duh sihtu adiz he jo gimmifali faffi nemeb zeb utoola wutofuh putouco ilriij. Tihgur wisor hehok zohoti sisbi gugit avjis rihla jizka nus tehicpit siv jezu ihabi zaosuna fah ajazi. Tiwbis hatehu ufe duz ecfod foducirus guw jiizref ruku nilokkar nef ebime. Wuorze vuj er kivzaj rovmugfi ta konwuvhag ehaushec nu navkef hipot sarvewev ta potferev kultarlap buhowfo keso. Epo ka hosfoj arti isera unurul he us jiuzu mu po te."
  },
  "apiKey": "11d62c9500dd2ecbdc2c42fa33930e642b1347f8c4da5e569cd47e1f8cf38f49",
  "currency": {
    "code": "CNY",
    "name": "China Yuan Renminbi"
  }
}