{
  "name": "Fannie Ruiz",
  "age": 49,
  "address": {
    "street": "Sumwed Center",
    "city": "Hurojve",
    "state": "VT",
    "zip": "03364"
  },
  "contact": {
    "phone": "(979) 824-6937",
    "servicePhone": "800521646"
  },
  "birthday": "1994-10-15T11:54:34.868Z",
  "ip": "89.1.67.238",
  "foo": "bar",
  "profile": {
    "about": "Gurlepkop fo kadiha urve hubugcak zihze bini li opapuvan huhla kivuali tubzeggof te sekebhu wubdeges. Oj rimidcif boc tih oke ozca bokhizwa mebum roetauze valigop enuem ma mah ivabice zaw wahbilel jeha co. Tafigu mo kimiw fig zuokiovo wubmu ruosawu wav sokfo icemo osaocvo gasfi cav. Tila razar romfocsuj kusuvdu lujre tutu opkuz riki ajuseb rihoziv fotperav bup mef ur ke non emniz. Ipbable zos olwu vogni pedugob gi duh amonupa kiz ka mezjeb optiv icos ij nimpu vitmu. Curnefat podbo uhroda wi wivrujwus ziado wojok wovucanic zobhevik odeah mac zus.",
    "bio": "Hiv midse ni mik ce fapu direhped wi ru gipow ci bizvi ezfate aduja cokku uti oha iz. Cohne cu te kodi jafuofi ti dus iweruvin miconwop riz ja jupe rapenu kese boj aki. Cucepwe kacu fezehif ra zo azo ji ogzucril hehopo muv logki mo. Dam ense hesge uwnutsa cuvus wucwar ricelas volevoz lew zodvikvev gosiamo tovgo. Eradzaf sittapnam ahijengo du geda meadi ri nepo fapri li gi nonulvop po hajvow. Afwur ho cadoz sejbarda tag okebub vahe pubi galogewe napab joaf lujwebuv savkec."
  },
  "apiKey": "b0f0c205ad4d0abb8b1b2e85f2a681ab1803fb574b875f0230e3dfb73a2d3685",
  "currency": {
    "code": "HRK",
    "name": "Croatia Kuna"
  }
}