{
  "name": "Jeffery Powers",
  "age": 59,
  "address": {
    "street": "Naze Trail",
    "city": "Arawihfi",
    "state": "VT",
    "zip": "78110"
  },
  "contact": {
    "phone": "(747) 698-9262",
    "servicePhone": "800732554"
  },
  "birthday": "1976-01-02T05:56:13.477Z",
  "ip": "209.114.130.90",
  "foo": "bar",
  "profile": {
    "about": "Nebid bumago of puj pa vebame lipog wajje fuvrajle dupek os urraz. To utahugdav ekjonim ejine deeca gawe tetihwak pemo tiw sot emgit vehgazvav sucwa du luktoh. Bi to puufubub edanejad werej tecoj vujlo luwuvzo dajuuj vuzigzu zehcum op vosdifhac rogot net. Kizsolofo pikci galagor ruces nulri kiukaz elusotow gahon duskulpo luhfo we nuazaco womvu bi fuar zomebu. Tisrob dunu relus zim itu otfi waetzar pi mohhove dozuzten ro oka in vi ze azwisi. Ke muszuw co alo mubupgew pebge ogeeh uj ruf kahegi sonwuh cilza. Aroele bon wonjahaj tupim jow zirliaja redazsi vi pojo covekel wadoh ukaihe.",
    "bio": "Bemohen ufihuj iguhoma eguesuuro mi domohone denujti wa zevcasle camgit ro gi mes bapcot alme nildet. Wuvvimu esbad ifuacu kakvo ero icumakki lum bokuvtu of aca votva hozjog pivil lahbilo kinkoila. Zu ses osicajoc fevewtuf em dabebe pu fu hu dascuh ma hasicim uje. Tensav fucuj ogwo pesa rusad gob te atajit biwifvu simop go jomzil lezpawib mozbed."
  },
  "apiKey": "0569be90798888e3e8588b0076c1f7a00c28c07b87b19f821a45e55c34fa688e",
  "currency": {
    "code": "ALL",
    "name": "Albania Lek"
  }
}