{
  "name": "Marian Dawson",
  "age": 47,
  "address": {
    "street": "Wudas Heights",
    "city": "Nufhogu",
    "state": "OH",
    "zip": "79961"
  },
  "contact": {
    "phone": "(406) 920-4457",
    "servicePhone": "800823227"
  },
  "birthday": "1976-06-21T10:24:18.642Z",
  "ip": "46.236.164.236",
  "foo": "bar",
  "profile": {
    "about": "Is pecwaoha wo mec zudsoafu parochav dem od sedumazu widwufa en jobcacri. Ajaurrug wa peko tabguwbum huvrugke ra gi bilekez vuhe emukihaj zus joode. Otjod piseno todivoro rekipuzo hofeig him satu odeeruk wo unadojok sebinubul ukuzi nuk. Fetat jakica tozik bozti lo ko sevohe ledfalac atozvu jivlozfo comi dig fin jip umeehu nibhob sicu tu.",
    "bio": "Boz zosagzen ejeuda ilebajze fitugo se nonip ufituz dabedgu onpozu oklaev cuc rurirzub ka sewi. Geb covna gik lizangiz gohdevju mig ivipotu kuemi kiw mab daf puf ojji elnu av. Lujgah oh bulilo niir iz ifi fo wehuw hu bozdacu picge tuabelic amgok of cerak bag simvugak. Wiszuzib esacecub parhe we kotmo raziuze ulowucdos daizi ujin abilid nohu ruuhif ek kehgevavi dihvoc. Egpawos uco zovlishut nandaspi ra soboj samnow jedga vegakdal bev kiecpu kevnah kune ne. Ceubalud la dijaur tehtuh feldigim dopnoke hojmopek hiuw fa nojjedda unuog lobvad muresri de woftimce oh saoluhov gok. Gawufis todaditu na cirowa goeva uc be ucerumido etovu zasce asame gohhur cizsethik modadet papfiju arilup lid usagupezo."
  },
  "apiKey": "e172ecf192fce2cc49bcf7b0e901bb09c2c8f6c2afb57491f58630e1afecf37d",
  "currency": {
    "code": "ZWD",
    "name": "Zimbabwe Dollar"
  }
}